odoo/addons/web_ir_actions_act_window_message/README.rst
odoo/addons/web_ir_actions_act_window_message/__init__.py
odoo/addons/web_ir_actions_act_window_message/__manifest__.py
odoo/addons/web_ir_actions_act_window_message/i18n/ar.po
odoo/addons/web_ir_actions_act_window_message/i18n/de.po
odoo/addons/web_ir_actions_act_window_message/i18n/es.po
odoo/addons/web_ir_actions_act_window_message/i18n/eu.po
odoo/addons/web_ir_actions_act_window_message/i18n/fi.po
odoo/addons/web_ir_actions_act_window_message/i18n/fr.po
odoo/addons/web_ir_actions_act_window_message/i18n/hr.po
odoo/addons/web_ir_actions_act_window_message/i18n/it.po
odoo/addons/web_ir_actions_act_window_message/i18n/nl.po
odoo/addons/web_ir_actions_act_window_message/i18n/nl_NL.po
odoo/addons/web_ir_actions_act_window_message/i18n/pt.po
odoo/addons/web_ir_actions_act_window_message/i18n/pt_BR.po
odoo/addons/web_ir_actions_act_window_message/i18n/ro.po
odoo/addons/web_ir_actions_act_window_message/i18n/sl.po
odoo/addons/web_ir_actions_act_window_message/i18n/tr.po
odoo/addons/web_ir_actions_act_window_message/i18n/web_ir_actions_act_window_message.pot
odoo/addons/web_ir_actions_act_window_message/readme/CONTRIBUTORS.rst
odoo/addons/web_ir_actions_act_window_message/readme/DESCRIPTION.rst
odoo/addons/web_ir_actions_act_window_message/readme/ROADMAP.rst
odoo/addons/web_ir_actions_act_window_message/readme/USAGE.rst
odoo/addons/web_ir_actions_act_window_message/static/description/icon.png
odoo/addons/web_ir_actions_act_window_message/static/description/index.html
odoo/addons/web_ir_actions_act_window_message/static/src/js/web_ir_actions_act_window_message.js
odoo/addons/web_ir_actions_act_window_message/static/src/xml/web_ir_actions_act_window_message.xml
odoo/addons/web_ir_actions_act_window_message/views/templates.xml
odoo13_addon_web_ir_actions_act_window_message-13.0.1.0.1.dev7.dist-info/METADATA
odoo13_addon_web_ir_actions_act_window_message-13.0.1.0.1.dev7.dist-info/WHEEL
odoo13_addon_web_ir_actions_act_window_message-13.0.1.0.1.dev7.dist-info/top_level.txt
odoo13_addon_web_ir_actions_act_window_message-13.0.1.0.1.dev7.dist-info/RECORD
